simple_bank/__init__.py
simple_bank/account.py
simple_bank/bank_operations.py
simple_bank_package-0.0.3.dist-info/METADATA
simple_bank_package-0.0.3.dist-info/WHEEL
simple_bank_package-0.0.3.dist-info/top_level.txt
simple_bank_package-0.0.3.dist-info/RECORD
