Metadata-Version: 2.1
Name: simple-bank-package
Version: 0.0.3
Summary: Simple functions for bank operation
Home-page: https://github.com/rvfalves/simple-package-template
Author: Rafael Alves
Author-email: rvf_alves@yahoo.com.br
Requires-Python: >=3.8
